putty_session_manager/__init__.py
putty_session_manager/__main__.py
putty_session_manager/operations.py
putty_session_manager/error/__init__.py
putty_session_manager/error/input_parameter_error.py
putty_session_manager/error/session_already_exists_error.py
putty_session_manager/error/session_attribute_not_found_error.py
putty_session_manager/error/session_not_found_error.py
putty_session_manager/format/__init__.py
putty_session_manager/format/utils.py
putty_session_manager/operation/__init__.py
putty_session_manager/operation/copy.py
putty_session_manager/operation/copy_attr.py
putty_session_manager/operation/create.py
putty_session_manager/operation/delete.py
putty_session_manager/operation/get.py
putty_session_manager/operation/list.py
putty_session_manager/registry/__init__.py
putty_session_manager/registry/utils.py
putty_session_manager-1.0.dev6.dist-info/LICENSE
putty_session_manager-1.0.dev6.dist-info/METADATA
putty_session_manager-1.0.dev6.dist-info/WHEEL
putty_session_manager-1.0.dev6.dist-info/entry_points.txt
putty_session_manager-1.0.dev6.dist-info/top_level.txt
putty_session_manager-1.0.dev6.dist-info/RECORD
