Metadata-Version: 2.1
Name: putty-session-manager
Version: 1.0.dev6
Summary: Python command-line utility for PuTTY session management
Home-page: https://github.com/mvelikikh/putty-session-manager
Author: Mikhail Velikikh
Author-email: mvelikikh@gmail.com
License: GNU General Public License (GPL)
Keywords: putty
Platform: UNKNOWN
Classifier: Development Status :: 4 - Beta
Classifier: Topic :: Internet
Classifier: Topic :: Software Development
Classifier: Topic :: Software Development :: Libraries
Classifier: License :: OSI Approved :: GNU General Public License (GPL)
Classifier: Intended Audience :: Developers
Classifier: Intended Audience :: System Administrators
Classifier: Operating System :: Microsoft :: Windows
Classifier: Programming Language :: Python :: 3.7
Requires-Dist: prettytable
